ocean/__init__.py
ocean/ocean.py
ocean/utils.py
ocean/modules/__init__.py
ocean/modules/aws_route53_handler.py
ocean/modules/git_hooks_handler.py
ocean/modules/logging_handler.py
ocean/modules/mixin_android.py
ocean/modules/mixin_atlantis.py
ocean/modules/mixin_autoupdate.py
ocean/modules/mixin_build_step.py
ocean/modules/mixin_buildstep_register.py
ocean/modules/mixin_buildstep_setcmd.py
ocean/modules/mixin_compute_environment.py
ocean/modules/mixin_criu.py
ocean/modules/mixin_crontab.py
ocean/modules/mixin_develop.py
ocean/modules/mixin_dkron.py
ocean/modules/mixin_extra_requirements.py
ocean/modules/mixin_freeze_unfreeze.py
ocean/modules/mixin_manifest.py
ocean/modules/mixin_misccmds.py
ocean/modules/mixin_repoapi.py
ocean/modules/mixin_tests.py
ocean/modules/network_attach_handler.py
ocean/modules/nginx_proxy_handler.py
ocean/modules/repo_bitbucket.py
ocean/modules/repo_github.py
ocean/modules/repo_gitlab.py
ocean/modules/template_handler.py
ocean/modules/vca.py
wideio_ocean-0.1.38.dist-info/DESCRIPTION.rst
wideio_ocean-0.1.38.dist-info/METADATA
wideio_ocean-0.1.38.dist-info/RECORD
wideio_ocean-0.1.38.dist-info/WHEEL
wideio_ocean-0.1.38.dist-info/entry_points.txt
wideio_ocean-0.1.38.dist-info/metadata.json
wideio_ocean-0.1.38.dist-info/top_level.txt
