Metadata-Version: 2.0
Name: wideio-ocean
Version: 0.1.38
Summary: OCEAN - A home-made utility to manage containerised development and testing environments
Home-page: https://github.com/wideioltd/ocean/
Author: WIDE IO LTD
Author-email: support@wide.io
License: BSD
Platform: UNKNOWN
Classifier: Development Status :: 3 - Alpha
Classifier: Intended Audience :: Developers
Classifier: Natural Language :: English
Classifier: License :: OSI Approved :: BSD License
Classifier: Programming Language :: Python
Classifier: Programming Language :: Python :: 2.7
Classifier: Programming Language :: Python :: 3.5
Classifier: Programming Language :: Python :: Implementation :: CPython
Requires-Dist: requests
Requires-Dist: functools32; python_version == "2.7"
